Workbook
Name Slicer_Region: #N/A

Sheet External Data
A1: Category | B1: Subcategory | C1: Supplier | D1: Brand | E1: Region | F1: Year | G1: Month | H1: Units Month | I1: Values Month | J1: Units YTD | K1: Values YTD | L1: Units MAT | M1: Values MAT
A2: Shampoo | B2: Anti-dandruff | C2: Apex Trading Co. | D2: RedRose | E2: Center | F2: 2018 | G2: 1 | H2: 11560 | I2: 62800 | J2: =SUMIFS(H:H,D:D,dataset_shampoo[[#This Row],[Brand]],E:E,dataset_shampoo[[#This Row],[Region]],F:F,dataset_shampoo[[#This Row],[Year]],G:G,"<="&dataset_shampoo[[#This Row],[Month]]) -> 11560 | K2: =SUMIFS(I:I,D:D,dataset_shampoo[[#This Row],[Brand]],E:E,dataset_shampoo[[#This Row],[Region]],F:F,dataset_shampoo[[#This Row],[Year]],G:G,"<="&dataset_shampoo[[#This Row],[Month]]) -> 62800 | L2: =dataset_shampoo[[#This Row],[Units YTD]]+SUMIFS(H:H,D:D,dataset_shampoo[[#This Row],[Brand]],E:E,dataset_shampoo[[#This Row],[Region]],F:F,dataset_shampoo[[#This Row],[Year]]-1,G:G,">"&dataset_shampoo[[#This Row],[Month]]) -> 11560 | M2: =dataset_shampoo[[#This Row],[Values YTD]]+SUMIFS(I:I,D:D,dataset_shampoo[[#This Row],[Brand]],E:E,dataset_shampoo[[#This Row],[Region]],F:F,dataset_shampoo[[#This Row],[Year]]-1,G:G,">"&dataset_shampoo[[#This Row],[Month]]) -> 62800
A3: Shampoo | B3: Anti-dandruff | C3: Apex Trading Co. | D3: RedRose | E3: Center | F3: 2018 | G3: 2 | H3: 10750 | I3: 58360 | J3: =SUMIFS(H:H,D:D,dataset_shampoo[[#This Row],[Brand]],E:E,dataset_shampoo[[#This Row],[Region]],F:F,dataset_shampoo[[#This Row],[Year]],G:G,"<="&dataset_shampoo[[#This Row],[Month]]) -> 22310 | K3: =SUMIFS(I:I,D:D,dataset_shampoo[[#This Row],[Brand]],E:E,dataset_shampoo[[#This Row],[Region]],F:F,dataset_shampoo[[#This Row],[Year]],G:G,"<="&dataset_shampoo[[#This Row],[Month]]) -> 121160 | L3: =dataset_shampoo[[#This Row],[Units YTD]]+SUMIFS(H:H,D:D,dataset_shampoo[[#This Row],[Brand]],E:E,dataset_shampoo[[#This Row],[Region]],F:F,dataset_shampoo[[#This Row],[Year]]-1,G:G,">"&dataset_shampoo[[#This Row],[Month]]) -> 22310 | M3: =dataset_shampoo[[#This Row],[Values YTD]]+SUMIFS(I:I,D:D,dataset_shampoo[[#This Row],[Brand]],E:E,dataset_shampoo[[#This Row],[Region]],F:F,dataset_shampoo[[#This Row],[Year]]-1,G:G,">"&dataset_shampoo[[#This Row],[Month]]) -> 121160
A4: Shampoo | B4: Anti-dandruff | C4: Apex Trading Co. | D4: RedRose | E4: Center | F4: 2018 | G4: 3 | H4: 11020 | I4: 59840 | J4: =SUMIFS(H:H,D:D,dataset_shampoo[[#This Row],[Brand]],E:E,dataset_shampoo[[#This Row],[Region]],F:F,dataset_shampoo[[#This Row],[Year]],G:G,"<="&dataset_shampoo[[#This Row],[Month]]) -> 33330 | K4: =SUMIFS(I:I,D:D,dataset_shampoo[[#This Row],[Brand]],E:E,dataset_shampoo[[#This Row],[Region]],F:F,dataset_shampoo[[#This Row],[Year]],G:G,"<="&dataset_shampoo[[#This Row],[Month]]) -> 181000 | L4: =dataset_shampoo[[#This Row],[Units YTD]]+SUMIFS(H:H,D:D,dataset_shampoo[[#This Row],[Brand]],E:E,dataset_shampoo[[#This Row],[Region]],F:F,dataset_shampoo[[#This Row],[Year]]-1,G:G,">"&dataset_shampoo[[#This Row],[Month]]) -> 33330 | M4: =dataset_shampoo[[#This Row],[Values YTD]]+SUMIFS(I:I,D:D,dataset_shampoo[[#This Row],[Brand]],E:E,dataset_shampoo[[#This Row],[Region]],F:F,dataset_shampoo[[#This Row],[Year]]-1,G:G,">"&dataset_shampoo[[#This Row],[Month]]) -> 181000
A5: Shampoo | B5: Anti-dandruff | C5: Apex Trading Co. | D5: RedRose | E5: Center | F5: 2018 | G5: 4 | H5: 11310 | I5: 61400 | J5: =SUMIFS(H:H,D:D,dataset_shampoo[[#This Row],[Brand]],E:E,dataset_shampoo[[#This Row],[Region]],F:F,dataset_shampoo[[#This Row],[Year]],G:G,"<="&dataset_shampoo[[#This Row],[Month]]) -> 44640 | K5: =SUMIFS(I:I,D:D,dataset_shampoo[[#This Row],[Brand]],E:E,dataset_shampoo[[#This Row],[Region]],F:F,dataset_shampoo[[#This Row],[Year]],G:G,"<="&dataset_shampoo[[#This Row],[Month]]) -> 242400 | L5: =dataset_shampoo[[#This Row],[Units YTD]]+SUMIFS(H:H,D:D,dataset_shampoo[[#This Row],[Brand]],E:E,dataset_shampoo[[#This Row],[Region]],F:F,dataset_shampoo[[#This Row],[Year]]-1,G:G,">"&dataset_shampoo[[#This Row],[Month]]) -> 44640 | M5: =dataset_shampoo[[#This Row],[Values YTD]]+SUMIFS(I:I,D:D,dataset_shampoo[[#This Row],[Brand]],E:E,dataset_shampoo[[#This Row],[Region]],F:F,dataset_shampoo[[#This Row],[Year]]-1,G:G,">"&dataset_shampoo[[#This Row],[Month]]) -> 242400
A6: Shampoo | B6: Anti-dandruff | C6: Apex Trading Co. | D6: RedRose | E6: Center | F6: 2018 | G6: 5 | H6: 13780 | I6: 74870 | J6: =SUMIFS(H:H,D:D,dataset_shampoo[[#This Row],[Brand]],E:E,dataset_shampoo[[#This Row],[Region]],F:F,dataset_shampoo[[#This Row],[Year]],G:G,"<="&dataset_shampoo[[#This Row],[Month]]) -> 58420 | K6: =SUMIFS(I:I,D:D,dataset_shampoo[[#This Row],[Brand]],E:E,dataset_shampoo[[#This Row],[Region]],F:F,dataset_shampoo[[#This Row],[Year]],G:G,"<="&dataset_shampoo[[#This Row],[Month]]) -> 317270 | L6: =dataset_shampoo[[#This Row],[Units YTD]]+SUMIFS(H:H,D:D,dataset_shampoo[[#This Row],[Brand]],E:E,dataset_shampoo[[#This Row],[Region]],F:F,dataset_shampoo[[#This Row],[Year]]-1,G:G,">"&dataset_shampoo[[#This Row],[Month]]) -> 58420 | M6: =dataset_shampoo[[#This Row],[Values YTD]]+SUMIFS(I:I,D:D,dataset_shampoo[[#This Row],[Brand]],E:E,dataset_shampoo[[#This Row],[Region]],F:F,dataset_shampoo[[#This Row],[Year]]-1,G:G,">"&dataset_shampoo[[#This Row],[Month]]) -> 317270
A7: Shampoo | B7: Anti-dandruff | C7: Apex Trading Co. | D7: RedRose | E7: Center | F7: 2018 | G7: 6 | H7: 13260 | I7: 72050 | J7: =SUMIFS(H:H,D:D,dataset_shampoo[[#This Row],[Brand]],E:E,dataset_shampoo[[#This Row],[Region]],F:F,dataset_shampoo[[#This Row],[Year]],G:G,"<="&dataset_shampoo[[#This Row],[Month]]) -> 71680 | K7: =SUMIFS(I:I,D:D,dataset_shampoo[[#This Row],[Brand]],E:E,dataset_shampoo[[#This Row],[Region]],F:F,dataset_shampoo[[#This Row],[Year]],G:G,"<="&dataset_shampoo[[#This Row],[Month]]) -> 389320 | L7: =dataset_shampoo[[#This Row],[Units YTD]]+SUMIFS(H:H,D:D,dataset_shampoo[[#This Row],[Brand]],E:E,dataset_shampoo[[#This Row],[Region]],F:F,dataset_shampoo[[#This Row],[Year]]-1,G:G,">"&dataset_shampoo[[#This Row],[Month]]) -> 71680 | M7: =dataset_shampoo[[#This Row],[Values YTD]]+SUMIFS(I:I,D:D,dataset_shampoo[[#This Row],[Brand]],E:E,dataset_shampoo[[#This Row],[Region]],F:F,dataset_shampoo[[#This Row],[Year]]-1,G:G,">"&dataset_shampoo[[#This Row],[Month]]) -> 389320
A8: Shampoo | B8: Anti-dandruff | C8: Apex Trading Co. | D8: RedRose | E8: Center | F8: 2018 | G8: 7 | H8: 11710 | I8: 63620 | J8: =SUMIFS(H:H,D:D,dataset_shampoo[[#This Row],[Brand]],E:E,dataset_shampoo[[#This Row],[Region]],F:F,dataset_shampoo[[#This Row],[Year]],G:G,"<="&dataset_shampoo[[#This Row],[Month]]) -> 83390 | K8: =SUMIFS(I:I,D:D,dataset_shampoo[[#This Row],[Brand]],E:E,dataset_shampoo[[#This Row],[Region]],F:F,dataset_shampoo[[#This Row],[Year]],G:G,"<="&dataset_shampoo[[#This Row],[Month]]) -> 452940 | L8: =dataset_shampoo[[#This Row],[Units YTD]]+SUMIFS(H:H,D:D,dataset_shampoo[[#This Row],[Brand]],E:E,dataset_shampoo[[#This Row],[Region]],F:F,dataset_shampoo[[#This Row],[Year]]-1,G:G,">"&dataset_shampoo[[#This Row],[Month]]) -> 83390 | M8: =dataset_shampoo[[#This Row],[Values YTD]]+SUMIFS(I:I,D:D,dataset_shampoo[[#This Row],[Brand]],E:E,dataset_shampoo[[#This Row],[Region]],F:F,dataset_shampoo[[#This Row],[Year]]-1,G:G,">"&dataset_shampoo[[#This Row],[Month]]) -> 452940
A9: Shampoo | B9: Anti-dandruff | C9: Apex Trading Co. | D9: RedRose | E9: Center | F9: 2018 | G9: 8 | H9: 12800 | I9: 69500 | J9: =SUMIFS(H:H,D:D,dataset_shampoo[[#This Row],[Brand]],E:E,dataset_shampoo[[#This Row],[Region]],F:F,dataset_shampoo[[#This Row],[Year]],G:G,"<="&dataset_shampoo[[#This Row],[Month]]) -> 96190 | K9: =SUMIFS(I:I,D:D,dataset_shampoo[[#This Row],[Brand]],E:E,dataset_shampoo[[#This Row],[Region]],F:F,dataset_shampoo[[#This Row],[Year]],G:G,"<="&dataset_shampoo[[#This Row],[Month]]) -> 522440 | L9: =dataset_shampoo[[#This Row],[Units YTD]]+SUMIFS(H:H,D:D,dataset_shampoo[[#This Row],[Brand]],E:E,dataset_shampoo[[#This Row],[Region]],F:F,dataset_shampoo[[#This Row],[Year]]-1,G:G,">"&dataset_shampoo[[#This Row],[Month]]) -> 96190 | M9: =dataset_shampoo[[#This Row],[Values YTD]]+SUMIFS(I:I,D:D,dataset_shampoo[[#This Row],[Brand]],E:E,dataset_shampoo[[#This Row],[Region]],F:F,dataset_shampoo[[#This Row],[Year]]-1,G:G,">"&dataset_shampoo[[#This Row],[Month]]) -> 522440
A10: Shampoo | B10: Anti-dandruff | C10: Apex Trading Co. | D10: RedRose | E10: Center | F10: 2018 | G10: 9 | H10: 9140 | I10: 49640 | J10: =SUMIFS(H:H,D:D,dataset_shampoo[[#This Row],[Brand]],E:E,dataset_shampoo[[#This Row],[Region]],F:F,dataset_shampoo[[#This Row],[Year]],G:G,"<="&dataset_shampoo[[#This Row],[Month]]) -> 105330 | K10: =SUMIFS(I:I,D:D,dataset_shampoo[[#This Row],[Brand]],E:E,dataset_shampoo[[#This Row],[Region]],F:F,dataset_shampoo[[#This Row],[Year]],G:G,"<="&dataset_shampoo[[#This Row],[Month]]) -> 572080 | L10: =dataset_shampoo[[#This Row],[Units YTD]]+SUMIFS(H:H,D:D,dataset_shampoo[[#This Row],[Brand]],E:E,dataset_shampoo[[#This Row],[Region]],F:F,dataset_shampoo[[#This Row],[Year]]-1,G:G,">"&dataset_shampoo[[#This Row],[Month]]) -> 105330 | M10: =dataset_shampoo[[#This Row],[Values YTD]]+SUMIFS(I:I,D:D,dataset_shampoo[[#This Row],[Brand]],E:E,dataset_shampoo[[#This Row],[Region]],F:F,dataset_shampoo[[#This Row],[Year]]-1,G:G,">"&dataset_shampoo[[#This Row],[Month]]) -> 572080
A11: Shampoo | B11: Anti-dandruff | C11: Apex Trading Co. | D11: RedRose | E11: Center | F11: 2018 | G11: 10 | H11: 11690 | I11: 63460 | J11: =SUMIFS(H:H,D:D,dataset_shampoo[[#This Row],[Brand]],E:E,dataset_shampoo[[#This Row],[Region]],F:F,dataset_shampoo[[#This Row],[Year]],G:G,"<="&dataset_shampoo[[#This Row],[Month]]) -> 117020 | K11: =SUMIFS(I:I,D:D,dataset_shampoo[[#This Row],[Brand]],E:E,dataset_shampoo[[#This Row],[Region]],F:F,dataset_shampoo[[#This Row],[Year]],G:G,"<="&dataset_shampoo[[#This Row],[Month]]) -> 635540 | L11: =dataset_shampoo[[#This Row],[Units YTD]]+SUMIFS(H:H,D:D,dataset_shampoo[[#This Row],[Brand]],E:E,dataset_shampoo[[#This Row],[Region]],F:F,dataset_shampoo[[#This Row],[Year]]-1,G:G,">"&dataset_shampoo[[#This Row],[Month]]) -> 117020 | M11: =dataset_shampoo[[#This Row],[Values YTD]]+SUMIFS(I:I,D:D,dataset_shampoo[[#This Row],[Brand]],E:E,dataset_shampoo[[#This Row],[Region]],F:F,dataset_shampoo[[#This Row],[Year]]-1,G:G,">"&dataset_shampoo[[#This Row],[Month]]) -> 635540
A12: Shampoo | B12: Anti-dandruff | C12: Apex Trading Co. | D12: RedRose | E12: Center | F12: 2018 | G12: 11 | H12: 9520 | I12: 51710 | J12: =SUMIFS(H:H,D:D,dataset_shampoo[[#This Row],[Brand]],E:E,dataset_shampoo[[#This Row],[Region]],F:F,dataset_shampoo[[#This Row],[Year]],G:G,"<="&dataset_shampoo[[#This Row],[Month]]) -> 126540 | K12: =SUMIFS(I:I,D:D,dataset_shampoo[[#This Row],[Brand]],E:E,dataset_shampoo[[#This Row],[Region]],F:F,dataset_shampoo[[#This Row],[Year]],G:G,"<="&dataset_shampoo[[#This Row],[Month]]) -> 687250 | L12: =dataset_shampoo[[#This Row],[Units YTD]]+SUMIFS(H:H,D:D,dataset_shampoo[[#This Row],[Brand]],E:E,dataset_shampoo[[#This Row],[Region]],F:F,dataset_shampoo[[#This Row],[Year]]-1,G:G,">"&dataset_shampoo[[#This Row],[Month]]) -> 126540 | M12: =dataset_shampoo[[#This Row],[Values YTD]]+SUMIFS(I:I,D:D,dataset_shampoo[[#This Row],[Brand]],E:E,dataset_shampoo[[#This Row],[Region]],F:F,dataset_shampoo[[#This Row],[Year]]-1,G:G,">"&dataset_shampoo[[#This Row],[Month]]) -> 687250
A13: Shampoo | B13: Anti-dandruff | C13: Apex Trading Co. | D13: RedRose | E13: Center | F13: 2018 | G13: 12 | H13: 13110 | I13: 71200 | J13: =SUMIFS(H:H,D:D,dataset_shampoo[[#This Row],[Brand]],E:E,dataset_shampoo[[#This Row],[Region]],F:F,dataset_shampoo[[#This Row],[Year]],G:G,"<="&dataset_shampoo[[#This Row],[Month]]) -> 139650 | K13: =SUMIFS(I:I,D:D,dataset_shampoo[[#This Row],[Brand]],E:E,dataset_shampoo[[#This Row],[Region]],F:F,dataset_shampoo[[#This Row],[Year]],G:G,"<="&dataset_shampoo[[#This Row],[Month]]) -> 758450 | L13: =dataset_shampoo[[#This Row],[Units YTD]]+SUMIFS(H:H,D:D,dataset_shampoo[[#This Row],[Brand]],E:E,dataset_shampoo[[#This Row],[Region]],F:F,dataset_shampoo[[#This Row],[Year]]-1,G:G,">"&dataset_shampoo[[#This Row],[Month]]) -> 139650 | M13: =dataset_shampoo[[#This Row],[Values YTD]]+SUMIFS(I:I,D:D,dataset_shampoo[[#This Row],[Brand]],E:E,dataset_shampoo[[#This Row],[Region]],F:F,dataset_shampoo[[#This Row],[Year]]-1,G:G,">"&dataset_shampoo[[#This Row],[Month]]) -> 758450
... A4433: Shampoo | B4433: Volumizing | C4433: HealthMax | D4433: Starbust | E4433: South | F4433: 2023 | G4433: 3 | H4433: 54215 | I4433: 340095 | J4433: =SUMIFS(H:H,D:D,dataset_shampoo[[#This Row],[Brand]],E:E,dataset_shampoo[[#This Row],[Region]],F:F,dataset_shampoo[[#This Row],[Year]],G:G,"<="&dataset_shampoo[[#This Row],[Month]]) -> 151683 | K4433: =SUMIFS(I:I,D:D,dataset_shampoo[[#This Row],[Brand]],E:E,dataset_shampoo[[#This Row],[Region]],F:F,dataset_shampoo[[#This Row],[Year]],G:G,"<="&dataset_shampoo[[#This Row],[Month]]) -> 938259 | L4433: =dataset_shampoo[[#This Row],[Units YTD]]+SUMIFS(H:H,D:D,dataset_shampoo[[#This Row],[Brand]],E:E,dataset_shampoo[[#This Row],[Region]],F:F,dataset_shampoo[[#This Row],[Year]]-1,G:G,">"&dataset_shampoo[[#This Row],[Month]]) -> 544411 | M4433: =dataset_shampoo[[#This Row],[Values YTD]]+SUMIFS(I:I,D:D,dataset_shampoo[[#This Row],[Brand]],E:E,dataset_shampoo[[#This Row],[Region]],F:F,dataset_shampoo[[#This Row],[Year]]-1,G:G,">"&dataset_shampoo[[#This Row],[Month]]) -> 3250114

Sheet Brands per Supplier
A3: Row Labels
A4: Apex Trading Co.
A5: Ocean Breeze
A6: Orchidea
A7: RedRose
A8: Wonder Waves | C8: Out of 25 brands in the market, HealthMax owns 2 - Shinez and Starbust.
A9: AquaSolutions
A10: Oasis
A11: Badoa
A12: Wild Flower
A13: Blue Sky Enterprises
A14: VelvetLux
A15: Elite Cosmetics
A16: Jasmine Mist
A17: FreshCo Industries
A18: Orchid Oasis
A19: Vitalize
A20: Glitterati
... A46: Grand Total

Sheet HealthMax YoY Growth
A1: Supplier | B1: HealthMax
A3: Sum of Values Month | B3: Column Labels
A4: Row Labels | B4: 2018 | C4: 2019 | D4: 2020 | E4: 2021 | F4: 2022 | G4: Grand Total
A5: Shinez | C5: -0.018851917 | D5: 0.076599056 | E5: 0.0089543838 | F5: 0.067382399
A6: Starbust | C6: -0.060152377 | D6: 0.017745775 | E6: 0.012423429 | F6: -9.1123768e-05
A7: Grand Total | C7: -0.046397508 | D7: 0.037912689 | E7: 0.011190404 | F7: 0.023838392
A10: In 2020, HealthMax grew by about 4%, indicating the strongest growth so far.

Sheet MAT Value Total Category
A1: Year | B1: 2023
A2: Month | B2: 3
A4: Sum of Values MAT
A5: 98452906
A7: Total turnover of the total shampoo category in the latest 12 months | G7: 98452906

Sheet Market Share
A3: Sum of Values Month | B3: Column Labels
A4: Row Labels | B4: Starbust | C4: Vitalize | D4: Harmonix | E4: Shinez | F4: Diamond Shine | G4: Ocean Breeze | H4: Orchid Oasis | I4: Oasis | J4: Nourish | K4: Lavender Bloom | L4: Mango Tango | M4: RedRose | N4: Orchidea | O4: VelvetLux | P4: Oceanic | Q4: Jasmine Mist | R4: Charisma | S4: Wild Flower | T4: Wonder Waves | U4: Sheen | V4: Enchantress | W4: Pure Radiance | X4: CitrusBurst | Y4: Golden Aura | Z4: Wave | AA4: Grand Total
A5: 2018 | B5: 0.23893363 | C5: 0.24638659 | D5: 0.12754938 | E5: 0.11931132 | F5: 0.042104527 | G5: 0.046637935 | H5: 0.029771546 | I5: 0.033728201 | J5: 0.028625371 | K5: 0.0041509526 | L5: 0.017584658 | M5: 0.021405196 | N5: 0.01074618 | O5: 0.00058849258 | P5: 0.0079070978 | Q5: 0 | R5: 0.0059910032 | S5: 0.001196272 | T5: 0.0031861222 | U5: 0.0035312824 | V5: 0.0012656554 | W5: 0.00073232634 | X5: 0.0024334058 | Y5: 0.0047140699 | Z5: 0.0015187947 | AA5: 1
A6: 2019 | B6: 0.217521 | C6: 0.22263199 | D6: 0.14634042 | E6: 0.11339207 | F6: 0.053918944 | G6: 0.037698899 | H6: 0.029143903 | I6: 0.033132302 | J6: 0.023720145 | K6: 0.009862904 | L6: 0.018911156 | M6: 0.019018917 | N6: 0.014647828 | O6: 0.020440558 | P6: 0.0074757063 | Q6: 0.00052674139 | R6: 0.0065457948 | S6: 0.0020406281 | T6: 0.005215563 | U6: 0.0034983893 | V6: 0.0030641086 | W6: 0.0033487738 | X6: 0.0021504253 | Y6: 0.0034329226 | Z6: 0.0023199103 | AA6: 1
A7: 2020 | B7: 0.22335758 | C7: 0.20944459 | D7: 0.15954757 | E7: 0.12316771 | F7: 0.051789283 | G7: 0.041879461 | H7: 0.029569828 | I7: 0.030564257 | J7: 0.020475056 | K7: 0.012714885 | L7: 0.017119546 | M7: 0.01699097 | N7: 0.015126111 | O7: 0.0084146922 | P7: 0.0072443011 | Q7: 0.0044224716 | R7: 0.0043184031 | S7: 0.0027634856 | T7: 0.0066702471 | U7: 0.0034161301 | V7: 0.0038840789 | W7: 0.0039159463 | X7: 0.0019472708 | Y7: 0.00081777227 | Z7: 0.00043835757 | AA7: 1
A8: 2021 | B8: 0.22410232 | C8: 0.20953737 | D8: 0.16390616 | E8: 0.12315495 | F8: 0.062925048 | G8: 0.029721332 | H8: 0.028101658 | I8: 0.027023175 | J8: 0.018460469 | K8: 0.024241525 | L8: 0.016624949 | M8: 0.015319404 | N8: 0.012164296 | O8: 0.0015229511 | P8: 0.0074553447 | Q8: 0.0073385965 | R8: 0.006320346 | S8: 0.0036902971 | T8: 0.0068737723 | U8: 0.0033344089 | V8: 0.0036711979 | W8: 0.0023037 | X8: 0.0020042705 | Y8: 0.00015584901 | Z8: 4.6604314e-05 | AA8: 1
A9: 2022 | B9: 0.21082811 | C9: 0.19176429 | D9: 0.18720457 | E9: 0.12367834 | F9: 0.063140114 | G9: 0.021197822 | H9: 0.038147589 | I9: 0.022912116 | J9: 0.015523076 | K9: 0.032752478 | L9: 0.013524828 | M9: 0.011268447 | N9: 0.011839652 | O9: 0.0069090824 | P9: 0.0067982714 | Q9: 0.015275613 | R9: 0.0054080696 | S9: 0.01028934 | T9: 0.00031902852 | U9: 0.0031339116 | V9: 0.003934834 | W9: 0.0023363403 | X9: 0.0017584548 | Y9: 4.9373461e-05 | Z9: 6.2554612e-06 | AA9: 1
A10: 2023 | B10: 0.2028326 | C10: 0.17748957 | D10: 0.18212524 | E10: 0.14499273 | F10: 0.087842706 | G10: 0.020220503 | H10: 0.024282124 | I10: 0.0064276913 | J10: 0.010788405 | K10: 0.046794427 | L10: 0.012542844 | M10: 0.0098052369 | N10: 0.010473185 | O10: 0.008560484 | P10: 0.0064535406 | Q10: 0.018529942 | R10: 0.0051217417 | S10: 0.013860303 | T10: 2.6072805e-05 | U10: 0.0032471071 | V10: 0.0037503122 | W10: 0.0022057593 | X10: 0.0015763618 | Y10: 5.1102697e-05 | Z10: 0 | AA10: 1
A11: Grand Total | B11: 0.2215638 | C11: 0.21330594 | D11: 0.15887386 | E11: 0.1219747 | F11: 0.056839111 | G11: 0.034315153 | H11: 0.030661314 | I11: 0.028053949 | J11: 0.020647781 | K11: 0.01872776 | L11: 0.016469353 | M11: 0.016308957 | N11: 0.012762607 | O11: 0.0076630213 | P11: 0.0073138158 | Q11: 0.0064044579 | R11: 0.0056798815 | S11: 0.0046512346 | T11: 0.0041555463 | U11: 0.003371214 | V11: 0.0032165036 | W11: 0.0025150758 | X11: 0.0020256948 | Y11: 0.0016959582 | Z11: 0.00080330182 | AA11: 1
A21: Insight: HealthMax is performing better in the South than in the rest of the country!

Sheet Internal Sales Data
A1: Brand | B1: Product | C1: Pack Size (ml) | D1: ProductID | E1: Retail Price | F1: Net Price | G1: COGS | H1: Volume 2022 | I1: Net Sales 2022 | J1: Gross Profit per unit | K1: Gross Profit per product | L1: Gross Margin | M1: Net Sales Contribution
A2: Starbust | B2: Ultra Soft | C2: 100 | D2: Starbust Ultra Soft 100ml | E2: 5 | F2: 3.1 | G2: 0.9 | H2: 1156348 | I2: =internal_sales_data[[#This Row],[Net Price]]*internal_sales_data[[#This Row],[Volume 2022]] -> 3584678.8 | J2: =internal_sales_data[[#This Row],[Net Price]]-internal_sales_data[[#This Row],[COGS]] -> 2.2 | K2: =internal_sales_data[[#This Row],[Gross Profit per unit]]*internal_sales_data[[#This Row],[Volume 2022]] -> 2543965.6 | L2: =internal_sales_data[[#This Row],[Gross Profit per product]]/internal_sales_data[[#This Row],[Net Sales 2022]] -> 0.70967742 | M2: =internal_sales_data[[#This Row],[Net Sales 2022]]/internal_sales_data[[#Totals],[Net Sales 2022]] -> 0.17502703
A3: Starbust | B3: Extra Shiny | C3: 100 | D3: Starbust Extra Shiny 100ml | E3: 5 | F3: 2.9 | G3: 0.95 | H3: 693809 | I3: =internal_sales_data[[#This Row],[Net Price]]*internal_sales_data[[#This Row],[Volume 2022]] -> 2012046.1 | J3: =internal_sales_data[[#This Row],[Net Price]]-internal_sales_data[[#This Row],[COGS]] -> 1.95 | K3: =internal_sales_data[[#This Row],[Gross Profit per unit]]*internal_sales_data[[#This Row],[Volume 2022]] -> 1352927.6 | L3: =internal_sales_data[[#This Row],[Gross Profit per product]]/internal_sales_data[[#This Row],[Net Sales 2022]] -> 0.67241379 | M3: =internal_sales_data[[#This Row],[Net Sales 2022]]/internal_sales_data[[#Totals],[Net Sales 2022]] -> 0.098241009
A4: Starbust | B4: Strong Hair | C4: 100 | D4: Starbust Strong Hair 100ml | E4: 5 | F4: 2.8 | G4: 1 | H4: 346904 | I4: =internal_sales_data[[#This Row],[Net Price]]*internal_sales_data[[#This Row],[Volume 2022]] -> 971331.2 | J4: =internal_sales_data[[#This Row],[Net Price]]-internal_sales_data[[#This Row],[COGS]] -> 1.8 | K4: =internal_sales_data[[#This Row],[Gross Profit per unit]]*internal_sales_data[[#This Row],[Volume 2022]] -> 624427.2 | L4: =internal_sales_data[[#This Row],[Gross Profit per product]]/internal_sales_data[[#This Row],[Net Sales 2022]] -> 0.64285714 | M4: =internal_sales_data[[#This Row],[Net Sales 2022]]/internal_sales_data[[#Totals],[Net Sales 2022]] -> 0.047426626
A5: Starbust | B5: Ultra Soft | C5: 150 | D5: Starbust Ultra Soft 150ml | E5: 7 | F5: 3.5 | G5: 1.2 | H5: 693809 | I5: =internal_sales_data[[#This Row],[Net Price]]*internal_sales_data[[#This Row],[Volume 2022]] -> 2428331.5 | J5: =internal_sales_data[[#This Row],[Net Price]]-internal_sales_data[[#This Row],[COGS]] -> 2.3 | K5: =internal_sales_data[[#This Row],[Gross Profit per unit]]*internal_sales_data[[#This Row],[Volume 2022]] -> 1595760.7 | L5: =internal_sales_data[[#This Row],[Gross Profit per product]]/internal_sales_data[[#This Row],[Net Sales 2022]] -> 0.65714286 | M5: =internal_sales_data[[#This Row],[Net Sales 2022]]/internal_sales_data[[#Totals],[Net Sales 2022]] -> 0.11856674
A6: Starbust | B6: Strong Hair | C6: 150 | D6: Starbust Strong Hair 150ml | E6: 7.25 | F6: 3.7 | G6: 1.3 | H6: 231270 | I6: =internal_sales_data[[#This Row],[Net Price]]*internal_sales_data[[#This Row],[Volume 2022]] -> 855699 | J6: =internal_sales_data[[#This Row],[Net Price]]-internal_sales_data[[#This Row],[COGS]] -> 2.4 | K6: =internal_sales_data[[#This Row],[Gross Profit per unit]]*internal_sales_data[[#This Row],[Volume 2022]] -> 555048 | L6: =internal_sales_data[[#This Row],[Gross Profit per product]]/internal_sales_data[[#This Row],[Net Sales 2022]] -> 0.64864865 | M6: =internal_sales_data[[#This Row],[Net Sales 2022]]/internal_sales_data[[#Totals],[Net Sales 2022]] -> 0.041780719
A7: Starbust | B7: Ultra Soft | C7: 200 | D7: Starbust Ultra Soft 200ml | E7: 9 | F7: 5 | G7: 1.5 | H7: 289087 | I7: =internal_sales_data[[#This Row],[Net Price]]*internal_sales_data[[#This Row],[Volume 2022]] -> 1445435 | J7: =internal_sales_data[[#This Row],[Net Price]]-internal_sales_data[[#This Row],[COGS]] -> 3.5 | K7: =internal_sales_data[[#This Row],[Gross Profit per unit]]*internal_sales_data[[#This Row],[Volume 2022]] -> 1011804.5 | L7: =internal_sales_data[[#This Row],[Gross Profit per product]]/internal_sales_data[[#This Row],[Net Sales 2022]] -> 0.7 | M7: =internal_sales_data[[#This Row],[Net Sales 2022]]/internal_sales_data[[#Totals],[Net Sales 2022]] -> 0.070575417
A8: Shinez | B8: Repair | C8: 100 | D8: Shinez Repair 100ml | E8: 6 | F8: 3.5 | G8: 1.15 | H8: 1089532 | I8: =internal_sales_data[[#This Row],[Net Price]]*internal_sales_data[[#This Row],[Volume 2022]] -> 3813362 | J8: =internal_sales_data[[#This Row],[Net Price]]-internal_sales_data[[#This Row],[COGS]] -> 2.35 | K8: =internal_sales_data[[#This Row],[Gross Profit per unit]]*internal_sales_data[[#This Row],[Volume 2022]] -> 2560400.2 | L8: =internal_sales_data[[#This Row],[Gross Profit per product]]/internal_sales_data[[#This Row],[Net Sales 2022]] -> 0.67142857 | M8: =internal_sales_data[[#This Row],[Net Sales 2022]]/internal_sales_data[[#Totals],[Net Sales 2022]] -> 0.18619282
A9: Shinez | B9: Repair | C9: 125 | D9: Shinez Repair 125ml | E9: 7 | F9: 4.25 | G9: 1.3 | H9: 466942 | I9: =internal_sales_data[[#This Row],[Net Price]]*internal_sales_data[[#This Row],[Volume 2022]] -> 1984503.5 | J9: =internal_sales_data[[#This Row],[Net Price]]-internal_sales_data[[#This Row],[COGS]] -> 2.95 | K9: =internal_sales_data[[#This Row],[Gross Profit per unit]]*internal_sales_data[[#This Row],[Volume 2022]] -> 1377478.9 | L9: =internal_sales_data[[#This Row],[Gross Profit per product]]/internal_sales_data[[#This Row],[Net Sales 2022]] -> 0.69411765 | M9: =internal_sales_data[[#This Row],[Net Sales 2022]]/internal_sales_data[[#Totals],[Net Sales 2022]] -> 0.096896203
A10: Shinez | B10: Repair | C10: 150 | D10: Shinez Repair 150ml | E10: 8 | F10: 5.1 | G10: 1.5 | H10: 389118 | I10: =internal_sales_data[[#This Row],[Net Price]]*internal_sales_data[[#This Row],[Volume 2022]] -> 1984501.8 | J10: =internal_sales_data[[#This Row],[Net Price]]-internal_sales_data[[#This Row],[COGS]] -> 3.6 | K10: =internal_sales_data[[#This Row],[Gross Profit per unit]]*internal_sales_data[[#This Row],[Volume 2022]] -> 1400824.8 | L10: =internal_sales_data[[#This Row],[Gross Profit per product]]/internal_sales_data[[#This Row],[Net Sales 2022]] -> 0.70588235 | M10: =internal_sales_data[[#This Row],[Net Sales 2022]]/internal_sales_data[[#Totals],[Net Sales 2022]] -> 0.09689612
A11: Shinez | B11: Repair | C11: 200 | D11: Shinez Repair 200ml | E11: 10 | F11: 6 | G11: 1.7 | H11: 233471 | I11: =internal_sales_data[[#This Row],[Net Price]]*internal_sales_data[[#This Row],[Volume 2022]] -> 1400826 | J11: =internal_sales_data[[#This Row],[Net Price]]-internal_sales_data[[#This Row],[COGS]] -> 4.3 | K11: =internal_sales_data[[#This Row],[Gross Profit per unit]]*internal_sales_data[[#This Row],[Volume 2022]] -> 1003925.3 | L11: =internal_sales_data[[#This Row],[Gross Profit per product]]/internal_sales_data[[#This Row],[Net Sales 2022]] -> 0.71666667 | M11: =internal_sales_data[[#This Row],[Net Sales 2022]]/internal_sales_data[[#Totals],[Net Sales 2022]] -> 0.068397319
A12: Total | H12: =SUBTOTAL(109,internal_sales_data[Volume 2022]) -> 5590290 | I12: =SUBTOTAL(109,internal_sales_data[Net Sales 2022]) -> 20480715 | K12: =SUBTOTAL(109,internal_sales_data[Gross Profit per product]) -> 14026563 | L12: =internal_sales_data[[#Totals],[Gross Profit per product]]/internal_sales_data[[#Totals],[Net Sales 2022]] -> 0.68486685
I14: 68.5% of the average net selling price is gross profit!

Sheet Profitability Matrix
A3: Sum of Net Sales Contribution | B3: Column Labels
A4: Row Labels | B4: 0.64285714 | C4: 0.64864865 | D4: 0.65714286 | E4: 0.67142857 | F4: 0.67241379 | G4: 0.69411765 | H4: 0.7 | I4: 0.70588235 | J4: 0.70967742 | K4: 0.71666667
A5: Shinez Repair 100ml | E5: 0.18619282
A6: Shinez Repair 125ml | G6: 0.096896203
A7: Shinez Repair 150ml | I7: 0.09689612
A8: Shinez Repair 200ml | K8: 0.068397319 | T8: Few insights: - Starbust Ultra Soft 100ML is the most important product in the assortment. - Shinez Repair 200ML is scoring relatively low in terms of net sales but is the most profitable product in the assortment.
A9: Starbust Extra Shiny 100ml | F9: 0.098241009
A10: Starbust Strong Hair 100ml | B10: 0.047426626
A11: Starbust Strong Hair 150ml | C11: 0.041780719
A12: Starbust Ultra Soft 100ml | J12: 0.17502703
A13: Starbust Ultra Soft 150ml | D13: 0.11856674
A14: Starbust Ultra Soft 200ml | H14: 0.070575417
A16: Row Labels | B16: 0.64285714 | C16: 0.64864865 | D16: 0.65714286 | E16: 0.67142857 | F16: 0.67241379 | G16: 0.69411765 | H16: 0.7 | I16: 0.70588235 | J16: 0.70967742 | K16: 0.71666667
A17: Shinez Repair 100ml | E17: 0.18619282
A18: Shinez Repair 125ml | G18: 0.096896203
A19: Shinez Repair 150ml | I19: 0.09689612
A20: Shinez Repair 200ml | K20: 0.068397319
A21: Starbust Extra Shiny 100ml | F21: 0.098241009
A22: Starbust Strong Hair 100ml | B22: 0.047426626
A23: Starbust Strong Hair 150ml | C23: 0.041780719
A24: Starbust Ultra Soft 100ml | J24: 0.17502703
A25: Starbust Ultra Soft 150ml | D25: 0.11856674
A26: Starbust Ultra Soft 200ml | H26: 0.070575417

Sheet New Category Opportunity
A3: Sum of Units Month | B3: Column Labels
A4: Row Labels | B4: 2018 | C4: 2022
A5: Anti-dandruff | C5: 0.11527757
A6: Color-safe | C6: -0.35222595
A7: Moisturizing | C7: 0.19140557
A8: Organic | C8: 2.7581984 | E8: Sub-category 'Organic' is the fastest growing.
A9: Volumizing | C9: -0.11045145
A11: Year | B11: 2023
A12: Month | B12: 3
A14: Row Labels | B14: Sum of Units MAT
A15: Organic | B15: 850749
A17: Estimated FY '24 Organic subcategory value | C17: =1.2*B15 -> 1020898.8

Sheet Organic Shampoo Launch
A1: Product | B1: Estimated Unit Market Share | C1: Estimated units sold 2024 | D1: Net Price | E1: Net Sales | F1: COGS | G1: Gross Profit per unit | H1: Gross Profit per product | I1: Gross Margin
A2: HerbEssentials | B2: 0.1 | C2: =new_product_launch[[#This Row],[Estimated Unit Market Share]]*'New Category Opportunity'!$C$17 -> 102089.88 | D2: 3.5 | E2: =new_product_launch[[#This Row],[Net Price]]*new_product_launch[[#This Row],[Estimated units sold 2024]] -> 357314.58 | F2: 1.35 | G2: =new_product_launch[[#This Row],[Net Price]]-new_product_launch[[#This Row],[COGS]] -> 2.15 | H2: =new_product_launch[[#This Row],[Gross Profit per unit]]*new_product_launch[[#This Row],[Estimated units sold 2024]] -> 219493.24 | I2: =new_product_launch[[#This Row],[Gross Profit per product]]/new_product_launch[[#This Row],[Net Sales]] -> 0.61428571
A3: Herbashine | B3: 0.12 | C3: =new_product_launch[[#This Row],[Estimated Unit Market Share]]*'New Category Opportunity'!$C$17 -> 122507.86 | D3: 2.75 | E3: =new_product_launch[[#This Row],[Net Price]]*new_product_launch[[#This Row],[Estimated units sold 2024]] -> 336896.6 | F3: 0.9 | G3: =new_product_launch[[#This Row],[Net Price]]-new_product_launch[[#This Row],[COGS]] -> 1.85 | H3: =new_product_launch[[#This Row],[Gross Profit per unit]]*new_product_launch[[#This Row],[Estimated units sold 2024]] -> 226639.53 | I3: =new_product_launch[[#This Row],[Gross Profit per product]]/new_product_launch[[#This Row],[Net Sales]] -> 0.67272727
A5: If Healthmax's goal is to increase their gross profit as much as possible, then they must launch Herbashine next year, as it will generate $0.34M in net sales. Herbashine will generate less net sales than HerbEssentials, but more gross profit!

Sheet 50ml Shampoo 2024
A1: Brand | B1: Product | C1: Pack Size (ml) | D1: ProductID | E1: Retail Price | F1: Net Price | G1: COGS | H1: Volume 2022 | I1: Net Sales 2022 | J1: Gross Profit per unit | K1: Gross Profit per product | L1: Gross Margin | M1: Price per ml
A2: Starbust | B2: Ultra Soft | C2: 100 | D2: Starbust Ultra Soft 100ml | E2: 5 | F2: 3.1 | G2: 0.9 | H2: 1156348 | I2: =internal_sales_data5[[#This Row],[Net Price]]*internal_sales_data5[[#This Row],[Volume 2022]] -> 3584678.8 | J2: =internal_sales_data5[[#This Row],[Net Price]]-internal_sales_data5[[#This Row],[COGS]] -> 2.2 | K2: =internal_sales_data5[[#This Row],[Gross Profit per unit]]*internal_sales_data5[[#This Row],[Volume 2022]] -> 2543965.6 | L2: =internal_sales_data5[[#This Row],[Gross Profit per product]]/internal_sales_data5[[#This Row],[Net Sales 2022]] -> 0.70967742 | M2: =internal_sales_data5[[#This Row],[Retail Price]]/internal_sales_data5[[#This Row],[Pack Size (ml)]] -> 0.05
A3: Starbust | B3: Extra Shiny | C3: 100 | D3: Starbust Extra Shiny 100ml | E3: 5 | F3: 2.9 | G3: 0.95 | H3: 693809 | I3: =internal_sales_data5[[#This Row],[Net Price]]*internal_sales_data5[[#This Row],[Volume 2022]] -> 2012046.1 | J3: =internal_sales_data5[[#This Row],[Net Price]]-internal_sales_data5[[#This Row],[COGS]] -> 1.95 | K3: =internal_sales_data5[[#This Row],[Gross Profit per unit]]*internal_sales_data5[[#This Row],[Volume 2022]] -> 1352927.6 | L3: =internal_sales_data5[[#This Row],[Gross Profit per product]]/internal_sales_data5[[#This Row],[Net Sales 2022]] -> 0.67241379 | M3: =internal_sales_data5[[#This Row],[Retail Price]]/internal_sales_data5[[#This Row],[Pack Size (ml)]] -> 0.05
A4: Starbust | B4: Strong Hair | C4: 100 | D4: Starbust Strong Hair 100ml | E4: 5 | F4: 2.8 | G4: 1 | H4: 346904 | I4: =internal_sales_data5[[#This Row],[Net Price]]*internal_sales_data5[[#This Row],[Volume 2022]] -> 971331.2 | J4: =internal_sales_data5[[#This Row],[Net Price]]-internal_sales_data5[[#This Row],[COGS]] -> 1.8 | K4: =internal_sales_data5[[#This Row],[Gross Profit per unit]]*internal_sales_data5[[#This Row],[Volume 2022]] -> 624427.2 | L4: =internal_sales_data5[[#This Row],[Gross Profit per product]]/internal_sales_data5[[#This Row],[Net Sales 2022]] -> 0.64285714 | M4: =internal_sales_data5[[#This Row],[Retail Price]]/internal_sales_data5[[#This Row],[Pack Size (ml)]] -> 0.05
A5: Starbust | B5: Ultra Soft | C5: 150 | D5: Starbust Ultra Soft 150ml | E5: 7 | F5: 3.5 | G5: 1.2 | H5: 693809 | I5: =internal_sales_data5[[#This Row],[Net Price]]*internal_sales_data5[[#This Row],[Volume 2022]] -> 2428331.5 | J5: =internal_sales_data5[[#This Row],[Net Price]]-internal_sales_data5[[#This Row],[COGS]] -> 2.3 | K5: =internal_sales_data5[[#This Row],[Gross Profit per unit]]*internal_sales_data5[[#This Row],[Volume 2022]] -> 1595760.7 | L5: =internal_sales_data5[[#This Row],[Gross Profit per product]]/internal_sales_data5[[#This Row],[Net Sales 2022]] -> 0.65714286 | M5: =internal_sales_data5[[#This Row],[Retail Price]]/internal_sales_data5[[#This Row],[Pack Size (ml)]] -> 0.046666667
A6: Starbust | B6: Strong Hair | C6: 150 | D6: Starbust Strong Hair 150ml | E6: 7.25 | F6: 3.7 | G6: 1.3 | H6: 231270 | I6: =internal_sales_data5[[#This Row],[Net Price]]*internal_sales_data5[[#This Row],[Volume 2022]] -> 855699 | J6: =internal_sales_data5[[#This Row],[Net Price]]-internal_sales_data5[[#This Row],[COGS]] -> 2.4 | K6: =internal_sales_data5[[#This Row],[Gross Profit per unit]]*internal_sales_data5[[#This Row],[Volume 2022]] -> 555048 | L6: =internal_sales_data5[[#This Row],[Gross Profit per product]]/internal_sales_data5[[#This Row],[Net Sales 2022]] -> 0.64864865 | M6: =internal_sales_data5[[#This Row],[Retail Price]]/internal_sales_data5[[#This Row],[Pack Size (ml)]] -> 0.048333333
A7: Starbust | B7: Ultra Soft | C7: 200 | D7: Starbust Ultra Soft 200ml | E7: 9 | F7: 5 | G7: 1.5 | H7: 289087 | I7: =internal_sales_data5[[#This Row],[Net Price]]*internal_sales_data5[[#This Row],[Volume 2022]] -> 1445435 | J7: =internal_sales_data5[[#This Row],[Net Price]]-internal_sales_data5[[#This Row],[COGS]] -> 3.5 | K7: =internal_sales_data5[[#This Row],[Gross Profit per unit]]*internal_sales_data5[[#This Row],[Volume 2022]] -> 1011804.5 | L7: =internal_sales_data5[[#This Row],[Gross Profit per product]]/internal_sales_data5[[#This Row],[Net Sales 2022]] -> 0.7 | M7: =internal_sales_data5[[#This Row],[Retail Price]]/internal_sales_data5[[#This Row],[Pack Size (ml)]] -> 0.045
A8: Shinez | B8: Repair | C8: 100 | D8: Shinez Repair 100ml | E8: 6 | F8: 3.5 | G8: 1.15 | H8: 1089532 | I8: =internal_sales_data5[[#This Row],[Net Price]]*internal_sales_data5[[#This Row],[Volume 2022]] -> 3813362 | J8: =internal_sales_data5[[#This Row],[Net Price]]-internal_sales_data5[[#This Row],[COGS]] -> 2.35 | K8: =internal_sales_data5[[#This Row],[Gross Profit per unit]]*internal_sales_data5[[#This Row],[Volume 2022]] -> 2560400.2 | L8: =internal_sales_data5[[#This Row],[Gross Profit per product]]/internal_sales_data5[[#This Row],[Net Sales 2022]] -> 0.67142857 | M8: =internal_sales_data5[[#This Row],[Retail Price]]/internal_sales_data5[[#This Row],[Pack Size (ml)]] -> 0.06
A9: Shinez | B9: Repair | C9: 125 | D9: Shinez Repair 125ml | E9: 7 | F9: 4.25 | G9: 1.3 | H9: 466942 | I9: =internal_sales_data5[[#This Row],[Net Price]]*internal_sales_data5[[#This Row],[Volume 2022]] -> 1984503.5 | J9: =internal_sales_data5[[#This Row],[Net Price]]-internal_sales_data5[[#This Row],[COGS]] -> 2.95 | K9: =internal_sales_data5[[#This Row],[Gross Profit per unit]]*internal_sales_data5[[#This Row],[Volume 2022]] -> 1377478.9 | L9: =internal_sales_data5[[#This Row],[Gross Profit per product]]/internal_sales_data5[[#This Row],[Net Sales 2022]] -> 0.69411765 | M9: =internal_sales_data5[[#This Row],[Retail Price]]/internal_sales_data5[[#This Row],[Pack Size (ml)]] -> 0.056
A10: Shinez | B10: Repair | C10: 150 | D10: Shinez Repair 150ml | E10: 8 | F10: 5.1 | G10: 1.5 | H10: 389118 | I10: =internal_sales_data5[[#This Row],[Net Price]]*internal_sales_data5[[#This Row],[Volume 2022]] -> 1984501.8 | J10: =internal_sales_data5[[#This Row],[Net Price]]-internal_sales_data5[[#This Row],[COGS]] -> 3.6 | K10: =internal_sales_data5[[#This Row],[Gross Profit per unit]]*internal_sales_data5[[#This Row],[Volume 2022]] -> 1400824.8 | L10: =internal_sales_data5[[#This Row],[Gross Profit per product]]/internal_sales_data5[[#This Row],[Net Sales 2022]] -> 0.70588235 | M10: =internal_sales_data5[[#This Row],[Retail Price]]/internal_sales_data5[[#This Row],[Pack Size (ml)]] -> 0.053333333
A11: Shinez | B11: Repair | C11: 200 | D11: Shinez Repair 200ml | E11: 10 | F11: 6 | G11: 1.7 | H11: 233471 | I11: =internal_sales_data5[[#This Row],[Net Price]]*internal_sales_data5[[#This Row],[Volume 2022]] -> 1400826 | J11: =internal_sales_data5[[#This Row],[Net Price]]-internal_sales_data5[[#This Row],[COGS]] -> 4.3 | K11: =internal_sales_data5[[#This Row],[Gross Profit per unit]]*internal_sales_data5[[#This Row],[Volume 2022]] -> 1003925.3 | L11: =internal_sales_data5[[#This Row],[Gross Profit per product]]/internal_sales_data5[[#This Row],[Net Sales 2022]] -> 0.71666667 | M11: =internal_sales_data5[[#This Row],[Retail Price]]/internal_sales_data5[[#This Row],[Pack Size (ml)]] -> 0.05
A12: Starbust | B12: Ultra Soft | C12: 50 | D12: Starbust Ultra Soft 50ml | E12: =1.5*M2*50 -> 3.75 | F12: 2.3 | G12: 0.7 | H12: =0.1*H2 -> 115634.8 | I12: =internal_sales_data5[[#This Row],[Net Price]]*internal_sales_data5[[#This Row],[Volume 2022]] -> 265960.04 | J12: =internal_sales_data5[[#This Row],[Net Price]]-internal_sales_data5[[#This Row],[COGS]] -> 1.6 | K12: =internal_sales_data5[[#This Row],[Gross Profit per unit]]*internal_sales_data5[[#This Row],[Volume 2022]] -> 185015.68 | L12: =internal_sales_data5[[#This Row],[Gross Profit per product]]/internal_sales_data5[[#This Row],[Net Sales 2022]] -> 0.69565217 | M12: =internal_sales_data5[[#This Row],[Retail Price]]/internal_sales_data5[[#This Row],[Pack Size (ml)]] -> 0.075

Sheet Promotion Graph
A1: Year | B1: 2022
A3: Row Labels | B3: Sum of Values Month
A4: Shinez | B4: 11625500
A5: 1 | B5: 849590
A6: 2 | B6: 822290
A7: 3 | B7: 827649
A8: 4 | B8: 1445626
A9: 5 | B9: 874089
A10: 6 | B10: 876087
A11: 7 | B11: 842454
A12: 8 | B12: 1198708
A13: 9 | B13: 853650
A14: 10 | B14: 816480
A15: 11 | B15: 1413646
A16: 12 | B16: 805231
A17: Grand Total | B17: 11625500

Sheet Promotion Analysis
A1: Promotion | B1: Mechanism | C1: Brand | D1: Year | E1: Month | F1: Value sales | G1: Baseline sales | H1: Uplift | I1: Costs | J1: ROI
A2: 1 | B2: Buy 2, get 1 free | C2: Shinez | D2: 2022 | E2: 4 | F2: =VLOOKUP(promotion_analysis[[#This Row],[Month]],'Promotion Graph'!$A$5:$B$16,2,FALSE) -> 1445626 | G2: =AVERAGEIFS('Promotion Graph'!$B$5:$B$16,'Promotion Graph'!$A$5:$A$16,"<>"&'Promotion Analysis'!$E$2,'Promotion Graph'!$A$5:$A$16,"<>"&'Promotion Analysis'!$E$3,'Promotion Graph'!$A$5:$A$16,"<>"&'Promotion Analysis'!$E$4) -> 840835.56 | H2: =promotion_analysis[[#This Row],[Value sales]]-promotion_analysis[[#This Row],[Baseline sales ]] -> 604790.44 | I2: 620000 | J2: =(promotion_analysis[[#This Row],[Uplift]]-promotion_analysis[[#This Row],[Costs]])/promotion_analysis[[#This Row],[Costs]] -> -0.024531541
A3: 2 | B3: Buy 2, get 20% off | C3: Shinez | D3: 2022 | E3: 8 | F3: =VLOOKUP(promotion_analysis[[#This Row],[Month]],'Promotion Graph'!$A$5:$B$16,2,FALSE) -> 1198708 | G3: =AVERAGEIFS('Promotion Graph'!$B$5:$B$16,'Promotion Graph'!$A$5:$A$16,"<>"&'Promotion Analysis'!$E$2,'Promotion Graph'!$A$5:$A$16,"<>"&'Promotion Analysis'!$E$3,'Promotion Graph'!$A$5:$A$16,"<>"&'Promotion Analysis'!$E$4) -> 840835.56 | H3: =promotion_analysis[[#This Row],[Value sales]]-promotion_analysis[[#This Row],[Baseline sales ]] -> 357872.44 | I3: 320000 | J3: =(promotion_analysis[[#This Row],[Uplift]]-promotion_analysis[[#This Row],[Costs]])/promotion_analysis[[#This Row],[Costs]] -> 0.11835139
A4: 3 | B4: 2nd at 50% off | C4: Shinez | D4: 2022 | E4: 11 | F4: =VLOOKUP(promotion_analysis[[#This Row],[Month]],'Promotion Graph'!$A$5:$B$16,2,FALSE) -> 1413646 | G4: =AVERAGEIFS('Promotion Graph'!$B$5:$B$16,'Promotion Graph'!$A$5:$A$16,"<>"&'Promotion Analysis'!$E$2,'Promotion Graph'!$A$5:$A$16,"<>"&'Promotion Analysis'!$E$3,'Promotion Graph'!$A$5:$A$16,"<>"&'Promotion Analysis'!$E$4) -> 840835.56 | H4: =promotion_analysis[[#This Row],[Value sales]]-promotion_analysis[[#This Row],[Baseline sales ]] -> 572810.44 | I4: 540000 | J4: =(promotion_analysis[[#This Row],[Uplift]]-promotion_analysis[[#This Row],[Costs]])/promotion_analysis[[#This Row],[Costs]] -> 0.060760082
A6: Buy 2, get 20% off is the most effective promotion.
A7: (The ROI for this promotion is 12% and is higher than Promotion #3. The ROI of Promotion #1 is negative and should not be repeated.)

Sheet Sales until 2022
A1: Supplier | B1: HealthMax
A3: Row Labels | B3: Sum of Values Month
A4: 2018 | B4: 30685269
A5: 2019 | B5: 29261549
A6: 2020 | B6: 30370933
A7: 2021 | B7: 30710796
A8: 2022 | B8: 31442892

Sheet Forecast 2024
A1: Timeline | B1: Market values | C1: Forecast | D1: Lower Confidence Bound | E1: Upper Confidence Bound | F1: Net Sales | G1: Ratio
A2: 2018 | B2: 30685269
A3: 2019 | B3: 29261549
A4: 2020 | B4: 30370933
A5: 2021 | B5: 30710796
A6: 2022 | B6: 31442892 | C6: 31442892 | D6: 31442892 | E6: 31442892 | F6: 20480715 | G6: =Table6[[#This Row],[Net Sales]]/Table6[[#This Row],[Market values]] -> 0.65136231
A7: 2023 | C7: =_xlfn.FORECAST.ETS(A7,$B$2:$B$6,$A$2:$A$6,1,1) -> 31635324 | D7: =C7-_xlfn.FORECAST.ETS.CONFINT(A7,$B$2:$B$6,$A$2:$A$6,0.95,1,1) -> 30014004 | E7: =C7+_xlfn.FORECAST.ETS.CONFINT(A7,$B$2:$B$6,$A$2:$A$6,0.95,1,1) -> 33256644 | F7: =Table6[[#This Row],[Forecast]]*$G$6 -> 20606058
A8: 2024 | C8: =_xlfn.FORECAST.ETS(A8,$B$2:$B$6,$A$2:$A$6,1,1) -> 31946448 | D8: =C8-_xlfn.FORECAST.ETS.CONFINT(A8,$B$2:$B$6,$A$2:$A$6,0.95,1,1) -> 30274836 | E8: =C8+_xlfn.FORECAST.ETS.CONFINT(A8,$B$2:$B$6,$A$2:$A$6,0.95,1,1) -> 33618060 | F8: =Table6[[#This Row],[Forecast]]*$G$6 -> 20808712

Sheet Waterfall
A1: Estimated net sales 2023 | B1: Natural growth | C1: Organic shampoo | D1: 50ml shampoo | E1: Estimated net sales 2024
A2: ='Forecast 2024'!F7 -> 20606058 | B2: ='Forecast 2024'!F8-'Forecast 2024'!F7 -> 202654.24 | C2: ='Organic Shampoo Launch'!E3 -> 336896.6 | D2: ='50ml Shampoo 2024'!I12 -> 265960.04 | E2: =SUM(A2:D2) -> 21411569
